fastfec/utils.py
fastfec/__init__.py
fastfec/client.py
fastfec/libfastfec.so
fastfec-0.4.1.dist-info/METADATA
fastfec-0.4.1.dist-info/WHEEL
fastfec-0.4.1.dist-info/RECORD
