Metadata-Version: 2.1
Name: fastfec
Version: 0.4.1
Summary: An extremely fast FEC filing parser written in C
Author: Washington Post News Engineering
License: MIT
Project-URL: Homepage, https://github.com/washingtonpost/FastFEC
Project-URL: Source Code, https://github.com/washingtonpost/FastFEC
Project-URL: Bug Tracker, https://github.com/washingtonpost/FastFEC/issues
Classifier: License :: OSI Approved :: MIT License
Requires-Python: ~=3.5
